pten/__init__.py
pten/keys.py
pten/notice.py
pten/wwapi.py
pten/wwcontact.py
pten/wwcrypt.py
pten/wwdoc.py
pten/wwmessager.py
pten-0.3.0.dist-info/LICENSE
pten-0.3.0.dist-info/METADATA
pten-0.3.0.dist-info/WHEEL
pten-0.3.0.dist-info/top_level.txt
pten-0.3.0.dist-info/RECORD
