Metadata-Version: 2.1
Name: pten
Version: 0.3.0
Summary: A tool to use Wechat work API quickly and easily
Home-page: https://github.com/bendell02/pten
Author: PENGyong
Author-email: 1203029076@qq.com
Keywords: wework qywx wechat weixin robot app
Classifier: Programming Language :: Python :: 3
Classifier: License :: OSI Approved :: MIT License
Classifier: Operating System :: OS Independent
Requires-Python: >=3.8
License-File: LICENSE
Requires-Dist: apscheduler
Requires-Dist: lunardate
Requires-Dist: openai
Requires-Dist: pycryptodome
